lender_datalayer/__init__.py
lender_datalayer/base_datalayer.py
lender_datalayer/custom_exception_handlers.py
lender_datalayer/redis_datalayer.py
lender_datalayer/common/__init__.py
lender_datalayer/common/constants.py
lender_datalayer/common/utils/__init__.py
lender_datalayer/common/utils/datetime_utils.py
lender_datalayer/common/utils/decorators.py
lender_datalayer/common/utils/encryption_utils.py
lender_datalayer/common/utils/random_value_generator_utils.py
lender_datalayer/ims_mappers/__init__.py
lender_datalayer/ims_mappers/account_mapper.py
lender_datalayer/ims_mappers/authentication_mapper.py
lender_datalayer/ims_mappers/bank_mapper.py
lender_datalayer/ims_mappers/config_mapper.py
lender_datalayer/ims_mappers/cp_dashboard_mapper.py
lender_datalayer/ims_mappers/cp_mapper.py
lender_datalayer/ims_mappers/document_mapper.py
lender_datalayer/ims_mappers/investor_mapper.py
lender_datalayer/ims_mappers/partner_mapper.py
lender_datalayer/ims_mappers/thirdparty_mapper.py
lender_datalayer/ims_mappers/txn_account_mapper.py
lender_datalayer/ios_mappers/__init__.py
lender_datalayer/ios_mappers/authentication_mapper.py
lender_datalayer/ios_mappers/bank_mapper.py
lender_datalayer/ios_mappers/bureau_mapper.py
lender_datalayer/ios_mappers/config_mapper.py
lender_datalayer/ios_mappers/cp_mapper.py
lender_datalayer/ios_mappers/dashboard_mapper.py
lender_datalayer/ios_mappers/document_mapper.py
lender_datalayer/ios_mappers/kmi_mapper.py
lender_datalayer/ios_mappers/thirdparty_hyperverge_mapper.py
lender_datalayer/ios_mappers/thirdparty_mapper.py
lender_datalayer/ios_mappers/user_mapper.py
lender_datalayer/ios_mappers/user_source_group_mapper.py
lender_datalayer/s2s_communication_mapper/s2s_communication.py
ldc_lender_datalayer-1.1.2.dist-info/METADATA
ldc_lender_datalayer-1.1.2.dist-info/WHEEL
ldc_lender_datalayer-1.1.2.dist-info/top_level.txt
ldc_lender_datalayer-1.1.2.dist-info/RECORD
