Metadata-Version: 2.4
Name: ldc-lender-datalayer
Version: 1.1.2
Summary: A comprehensive data access layer for ldc lender apps
Author: Sandesh Kanagal
Author-email: sandesh.kanagal@lendenclub.com
Maintainer: Sonu Sharma
Maintainer-email: sonu.sharma@lendenclub.com
Classifier: Intended Audience :: Developers
Classifier: Programming Language :: Python :: 3
Classifier: Topic :: Utilities
Requires-Python: >=3.10.0
Requires-Dist: Django>=5.2.0
Requires-Dist: psycopg[binary,pool]>=3.2.9
Requires-Dist: redis>=5.0.3
Requires-Dist: pytz>=2023.3
Requires-Dist: python-dateutil>=2.8.2
Requires-Dist: pycryptodome>=3.19.0
Dynamic: author
Dynamic: author-email
Dynamic: classifier
Dynamic: description
Dynamic: description-content-type
Dynamic: maintainer
Dynamic: maintainer-email
Dynamic: requires-dist
Dynamic: requires-python
Dynamic: summary
